flask_widgets.py
Flask_Widgets-0.5.dist-info/LICENSE
Flask_Widgets-0.5.dist-info/METADATA
Flask_Widgets-0.5.dist-info/WHEEL
Flask_Widgets-0.5.dist-info/top_level.txt
Flask_Widgets-0.5.dist-info/RECORD
